{
    "users": {
        "user1": {
            "password": "password1",
            "data2": "value2",
            "data3": "value3"
        },
        "user2": {
            "data1": "password2",
            "data2": "value2",
            "data3": "value3"
        },
        "user3": {
            "data1": "password3",
            "data2": "value2",
            "data3": "value3"
        }
    },
    "goods": {
        "1": {
            "name": "Apple",
            "price": 1,
            "count": "value2"
        },
        "2": {
            "name": "Banana",
            "price": 2,
            "count": "value2"
        },
        "3": {
            "name": "Fish",
            "price": 3,
            "count": "value2"
        }
    }
}